setup.py
client/__init__.py
client/client.py
client/apr_doc/__init__.py
client/apr_doc/source/__init__.py
client/apr_doc/source/conf.py
client/client/__init__.py
client/client/add_contact.py
client/client/client_database.py
client/client/delete_contact.py
client/client/main_window.py
client/client/main_window_conv.py
client/client/start_dialog.py
client/client/transport.py
client/common/__init__.py
client/common/decor.py
client/common/descriptrs.py
client/common/metaclasses.py
client/common/utils.py
client/common/variables.py
client/log/__init__.py
client/log/configs/__init__.py
client/log/configs/client_log_config.py
client/log/configs/server_log_config.py
message_client_zda.egg-info/PKG-INFO
message_client_zda.egg-info/SOURCES.txt
message_client_zda.egg-info/dependency_links.txt
message_client_zda.egg-info/requires.txt
message_client_zda.egg-info/top_level.txt