Metadata-Version: 1.0
Name: message-client-zda
Version: 0.0.1
Summary: message_client_zda
Home-page: UNKNOWN
Author: Dmitrii Zarubin
Author-email: zda_87@mail.ru
License: UNKNOWN
Platform: UNKNOWN
